automatic_cv/__init__.py
automatic_cv/_version.py
automatic_cv/base_programs.py
automatic_cv/common.py
automatic_cv/device.py
automatic_cv/find_devices.py
automatic_cv/program.py
automatic_cv/techniques_version.json
automatic_cv/lib/__init__.py
automatic_cv/lib/data_parser.py
automatic_cv/lib/ec_errors.py
automatic_cv/lib/ec_find.py
automatic_cv/lib/ec_lib.py
automatic_cv/lib/technique_fields.py
automatic_cv/techniques-6.04/EClib.dll
automatic_cv/techniques-6.04/EClib64.dll
automatic_cv/techniques-6.04/IRcmp.ecc
automatic_cv/techniques-6.04/IRcmp4.ecc
automatic_cv/techniques-6.04/TI.ecc
automatic_cv/techniques-6.04/TI4.ecc
automatic_cv/techniques-6.04/TO.ecc
automatic_cv/techniques-6.04/TO4.ecc
automatic_cv/techniques-6.04/TOS.ecc
automatic_cv/techniques-6.04/TOS4.ecc
automatic_cv/techniques-6.04/Vmp_ii_0437_a6.xlx
automatic_cv/techniques-6.04/Vmp_iv_0395_aa.xlx
automatic_cv/techniques-6.04/biovscan.ecc
automatic_cv/techniques-6.04/blfind.dll
automatic_cv/techniques-6.04/blfind64.dll
automatic_cv/techniques-6.04/ca.ecc
automatic_cv/techniques-6.04/ca4.ecc
automatic_cv/techniques-6.04/calimit.ecc
automatic_cv/techniques-6.04/calimit4.ecc
automatic_cv/techniques-6.04/casg.ecc
automatic_cv/techniques-6.04/casg4.ecc
automatic_cv/techniques-6.04/casp.ecc
automatic_cv/techniques-6.04/casp4.ecc
automatic_cv/techniques-6.04/cp.ecc
automatic_cv/techniques-6.04/cp4.ecc
automatic_cv/techniques-6.04/cplimit.ecc
automatic_cv/techniques-6.04/cplimit4.ecc
automatic_cv/techniques-6.04/cpp.ecc
automatic_cv/techniques-6.04/cpp4.ecc
automatic_cv/techniques-6.04/cv.ecc
automatic_cv/techniques-6.04/cv4.ecc
automatic_cv/techniques-6.04/dnpv.ecc
automatic_cv/techniques-6.04/dnpv4.ecc
automatic_cv/techniques-6.04/dpa.ecc
automatic_cv/techniques-6.04/dpa4.ecc
automatic_cv/techniques-6.04/dpv.ecc
automatic_cv/techniques-6.04/dpv4.ecc
automatic_cv/techniques-6.04/evt.ecc
automatic_cv/techniques-6.04/evt4.ecc
automatic_cv/techniques-6.04/gc.ecc
automatic_cv/techniques-6.04/gc4.ecc
Automatic_CV-1.0.0.dist-info/LICENSE
Automatic_CV-1.0.0.dist-info/METADATA
Automatic_CV-1.0.0.dist-info/WHEEL
Automatic_CV-1.0.0.dist-info/top_level.txt
Automatic_CV-1.0.0.dist-info/RECORD
