Metadata-Version: 2.1
Name: Automatic-CV
Version: 1.0.0
Summary: Control the Biologic potentiostat to test CV experiment via Python (combination with OT-2)
Home-page: 
Author: Danger Lin
Author-email: dangerlin100@gmail.com
Project-URL: Source Code, https://github.com/DangerLin/Automatic-CV
Project-URL: Bug Tracker, https://github.com/DangerLin/Automatic-CV/issues
Keywords: biologic
Classifier: Programming Language :: Python :: 3
Classifier: License :: OSI Approved :: GNU General Public License v3 (GPLv3)
Classifier: Operating System :: Microsoft :: Windows
Classifier: Development Status :: 3 - Alpha
Requires-Python: >=3.7
License-File: LICENSE
